sibyl_scope-0.1.0.dist-info/licenses/LICENSE
sybil_scope/__init__.py
sybil_scope/_version.py
sybil_scope/api.py
sybil_scope/backend.py
sybil_scope/config.py
sybil_scope/core.py
sybil_scope/decorators.py
sybil_scope/integrations/__init__.py
sybil_scope/integrations/langchain.py
sybil_scope/viewer/__init__.py
sybil_scope/viewer/__main__.py
sybil_scope/viewer/app.py
sybil_scope/viewer/common.py
sybil_scope/viewer/flow_diagram.py
sybil_scope/viewer/hierarchical_view.py
sybil_scope/viewer/table_view.py
sybil_scope/viewer/timeline.py
sibyl_scope-0.1.0.dist-info/METADATA
sibyl_scope-0.1.0.dist-info/WHEEL
sibyl_scope-0.1.0.dist-info/top_level.txt
sibyl_scope-0.1.0.dist-info/RECORD
