Metadata-Version: 2.4
Name: sibyl-scope
Version: 0.1.0
Summary: Comprehensive tracing and observability toolkit for Python AI/LLM applications
Requires-Python: >=3.10
License-File: LICENSE
Requires-Dist: pydantic>=2.11.5
Dynamic: license-file
